odk_tools/__init__.py
odk_tools/classes.py
odk_tools/functions.py
odk_tools/odk.py
odk_tools-0.2.6.dist-info/METADATA
odk_tools-0.2.6.dist-info/WHEEL
odk_tools-0.2.6.dist-info/licenses/LICENSE
odk_tools-0.2.6.dist-info/RECORD
